fluentmetrics
tests
