Metadata-Version: 2.1
Name: cloudwatch-fluent-metrics
Version: 0.5.2
Summary: AWS CloudWatch Fluent Metrics
Home-page: https://github.com/awslabs/cloudwatch-fluent-metrics
Author: troylar
Author-email: troylars@amazon.com
License: Apache-2.0
Download-URL: https://github.com/awslabs/cloudwatch-fluent-metrics/cloudwatch-fluent-metrics-v0.1.tgz
Keywords: metrics,logging,aws,cloudwatch
Platform: UNKNOWN
Classifier: Development Status :: 5 - Production/Stable
Classifier: Topic :: Utilities
Classifier: License :: OSI Approved :: Apache Software License
